labrat/catcher.py
labrat/app.py
labrat/__init__.py
labrat/convert.py
labrat-0.1.1.dist-info/WHEEL
labrat-0.1.1.dist-info/METADATA
labrat-0.1.1.dist-info/top_level.txt
labrat-0.1.1.dist-info/RECORD
labrat-0.1.1.dist-info/metadata.json
labrat-0.1.1.dist-info/entry_points.txt
labrat-0.1.1.dist-info/DESCRIPTION.rst
