Metadata-Version: 2.0
Name: labrat
Version: 0.1.1
Summary: CIELAB color picker
Home-page: http://jangler.info/code/labrat
Author: Brandon Mulcahy
Author-email: brandon@jangler.info
License: MIT
Keywords: cie,cielab,color,lab,labrat,rgb
Platform: UNKNOWN
Classifier: Development Status :: 4 - Beta
Classifier: Intended Audience :: End Users/Desktop
Classifier: License :: OSI Approved :: MIT License
Classifier: Operating System :: OS Independent
Classifier: Programming Language :: Python
Classifier: Programming Language :: Python :: 3
Classifier: Programming Language :: Python :: 3 :: Only
Classifier: Topic :: Multimedia
Classifier: Topic :: Multimedia :: Graphics
